[
  {
    "Male":"Votre personnage est-il de sexe masculin?",
    "Femelle":"Votre personnage est-il de sexe feminin?",
    "Humain":"Le personnage est-il humain?",
    "Super-Heros":"Le personnage est-il un super-héro?",
    "Petit":"Votre personnage est-il petit?",
    "Moyen":"Votre personnage est-il moyen?",
    "Grand":"Votre personnage est-il Grand?",
    "Pouvoir":"Le personnage possède t-il des pouvoirs?",
    "Vole":"Le personnage vole-t-il?",
    "Force":"Le personnage est-il fort?",
    "Cape":"Le personnage possède t-il une cape?",
    "Adulte":"Le personnage est-il un adulte?",
    "Animal":"Le personnage est-il un animal?",
    "Intelligence":"Le personnage est-il intelligent?",
    "Fait_des_betises":"Le personnage fait-il des bêtises?",
    "Gentil":"Le personnage est-il gentil?",
    "Se_battre":"Le personnage est-il baguarreur?",
    "Poilu":"Le personnage est-il poilu?",
    "Parole":"Le personnage parle t-il?",
    "Aquatique":"Est-ce un personnage aquatique?",
    "Transformation":"Le personnage se transforme t-il?",
    "Jaune":"Le personnage a-t-il du jaune sur lui?",
    "Vert":"Le personnage a-t-il vert sur lui?",
    "Bleu":"Le personnage a-t-il bleu sur lui?",
    "Rouge":"Le personnage a-t-il rouge sur lui?",
    "Marron":"Le personnage a-t-il marron sur lui?"
  }
]